opsduty_python/__init__.py
opsduty_python/cli/__init__.py
opsduty_python/cli/__main__.py
opsduty_python/cli/cli_groups.py
opsduty_python/cli/heartbeats/__init__.py
opsduty_python/cli/heartbeats/checkin.py
opsduty_python/cli/heartbeats/export.py
opsduty_python/cli/heartbeats/import.py
opsduty_python/cli/heartbeats/records.py
opsduty_python/cli/mutex.py
opsduty_python/cli/schedules/__init__.py
opsduty_python/cli/schedules/records.py
opsduty_python/cli/schedules/shifts.py
opsduty_python/cli/utils.py
opsduty_python/heartbeats/__init__.py
opsduty_python/heartbeats/heartbeats.py
opsduty_python/py.typed
opsduty_python/settings.py
opsduty_python/utils/__init__.py
opsduty_python/utils/logging.py
opsduty_python-0.2.4.dist-info/LICENSE
opsduty_python-0.2.4.dist-info/METADATA
opsduty_python-0.2.4.dist-info/WHEEL
opsduty_python-0.2.4.dist-info/entry_points.txt
opsduty_python-0.2.4.dist-info/RECORD
