Metadata-Version: 2.1
Name: opsduty-python
Version: 0.2.4
Summary: Command-line utility for interfacing with OpsDuty.
License: MIT
Author: Eirik Martiniussen Sylliaas
Author-email: eirik@opsduty.io
Requires-Python: >=3.11,<3.14
Classifier: License :: OSI Approved :: MIT License
Classifier: Programming Language :: Python :: 3
Classifier: Programming Language :: Python :: 3.11
Classifier: Programming Language :: Python :: 3.12
Requires-Dist: click (>=8.1.7,<9)
Requires-Dist: opsduty-client (>=0.0.7,<0.0.8)
Requires-Dist: pydantic (>=2.8,<3)
Requires-Dist: pydantic-yaml (>=1.3.0,<2)
Requires-Dist: requests (>=2.32,<3)
Requires-Dist: structlog
Requires-Dist: urllib3 (>=2.2.2,<3)
